ibis_datasette/__init__.py
ibis_datasette/_version.py
ibis_datasette/core.py
ibis_datasette-0.2.2.dist-info/LICENSE
ibis_datasette-0.2.2.dist-info/METADATA
ibis_datasette-0.2.2.dist-info/WHEEL
ibis_datasette-0.2.2.dist-info/entry_points.txt
ibis_datasette-0.2.2.dist-info/top_level.txt
ibis_datasette-0.2.2.dist-info/RECORD
