Metadata-Version: 2.1
Name: ibis-datasette
Version: 0.2.2
Summary: An ibis backend for querying datasette
Home-page: https://github.com/jcrist/ibis-datasette
Maintainer: Jim Crist-Harif
Maintainer-email: jcristharif@gmail.com
License: BSD
Project-URL: Source, https://github.com/jcrist/ibis-datasette/
Project-URL: Issue Tracker, https://github.com/jcrist/ibis-datasette/issues
Keywords: ibis datasette pandas sqlite
Classifier: License :: OSI Approved :: BSD License
Classifier: Programming Language :: Python :: 3.8
Classifier: Programming Language :: Python :: 3.9
Classifier: Programming Language :: Python :: 3.10
Requires-Python: >=3.8
License-File: LICENSE
Requires-Dist: httpx
Requires-Dist: ibis-framework
Requires-Dist: sqlalchemy
